mu32/__init__.py
mu32/__main__.py
mu32/beamformer.py
mu32/core.py
mu32/core_base.py
mu32/core_h5.old.py
mu32/core_h5.py
mu32/core_rand.py
mu32/core_server.py
mu32/core_types.py
mu32/core_ws.py
mu32/exception.py
mu32/log.py
mu32/synthesis.py
mu32/apps/__init__.py
mu32/apps/mu32server.py
mu32/apps/mu32usbcheck.py
mu32/apps/muH5check.py
mu32/examples/__init__.py
mu32/examples/mu256h5save.py
mu32/examples/mu256run.py
mu32/examples/mu32autotest.py
mu32/examples/mu32cv.py
mu32/examples/mu32doa.py
mu32/examples/mu32graph.py
mu32/examples/mu32h5save.py
mu32/examples/mu32play.py
mu32/examples/mu32plot.py
mu32/examples/mu32power.py
mu32/examples/mu32rms_map.py
mu32/examples/mu32run.py
mu32/examples/mu32save.py
mu32/examples/mu32spectrum.py
mu32/examples/mu32wav.py
mu32/examples/mu32wsH5play.py
mu32/examples/mu32wsaudio.py
mu32/examples/mu32wsgraph.py
mu32/examples/mu32wsh5.py
mu32/examples/mu32wsh5audio.py
mu32/examples/mu32wsplot.py
mu32/examples/mu32wsrun.py
mu32/examples/mu32wssave.py
mu32/examples/mu32wsscheduler.py
mu32/examples/muH5audio.py
mu32/examples/muH5autotest.py
mu32/examples/muH5play.py
mu32/jupyter/__init__.py
mu32/tests/__init__.py
mu32/tests/mu32OneChannelView.py
mu32/tests/mu32RMS.py
mu32/tests/mu32RMS_Map.py
mu32/tests/mu32dash.py
mu32/tests/mu32dash2.py
mu32/tests/mu32plot2.py
mu32/tests/mu32plot3.py
mu32/tests/mu32run2.py
mu32/tests/mu32run2b.py
mu32/tests/mu32ws_client.py
mu32/tests/videoCapture.py
mu32-0.1.7.dist-info/LICENSE
mu32-0.1.7.dist-info/METADATA
mu32-0.1.7.dist-info/WHEEL
mu32-0.1.7.dist-info/entry_points.txt
mu32-0.1.7.dist-info/top_level.txt
mu32-0.1.7.dist-info/RECORD
