Metadata-Version: 2.1
Name: mu32
Version: 0.1.7
Summary: Mu32 receiver program interface
Home-page: https://github.com/distalsense/mu32
Author: Bruno Gas
Author-email: bruno.gas@distalsense.com
Project-URL: Documentation, https://distalsense.io
Project-URL: Bug Tracker, https://github.com/distalsense/mu32/issues
Classifier: Programming Language :: Python :: 3
Classifier: License :: OSI Approved :: GNU General Public License (GPL)
Classifier: Operating System :: OS Independent
Classifier: Development Status :: 2 - Pre-Alpha
Classifier: Natural Language :: English
Requires-Python: >=3.6
License-File: LICENSE
Requires-Dist: libusb1
Requires-Dist: numpy
Requires-Dist: scipy
Requires-Dist: matplotlib
Requires-Dist: sounddevice
Requires-Dist: h5py
Requires-Dist: websockets
Requires-Dist: opencv-python
